<annotation>
	<folder>JPEGImages</folder>
	<filename>2484.jpg</filename>
	<path>G:\ustc\bishe\dataset\JPEGImages\2484.jpg</path>
	<source>
		<database>Unknown</database>
	</source>
	<size>
		<width>640</width>
		<height>480</height>
		<depth>3</depth>
	</size>
	<segmented>0</segmented>
	<object>
		<name>closed_eye</name>
		<pose>Unspecified</pose>
		<truncated>0</truncated>
		<difficult>0</difficult>
		<bndbox>
			<xmin>349</xmin>
			<ymin>236</ymin>
			<xmax>385</xmax>
			<ymax>252</ymax>
		</bndbox>
	</object>
	<object>
		<name>closed_eye</name>
		<pose>Unspecified</pose>
		<truncated>0</truncated>
		<difficult>0</difficult>
		<bndbox>
			<xmin>292</xmin>
			<ymin>212</ymin>
			<xmax>324</xmax>
			<ymax>232</ymax>
		</bndbox>
	</object>
	<object>
		<name>closed_mouth</name>
		<pose>Unspecified</pose>
		<truncated>0</truncated>
		<difficult>0</difficult>
		<bndbox>
			<xmin>300</xmin>
			<ymin>278</ymin>
			<xmax>344</xmax>
			<ymax>303</ymax>
		</bndbox>
	</object>
</annotation>
