<annotation>
	<folder>JPEGImages</folder>
	<filename>1935.jpg</filename>
	<path>G:\ustc\bishe\dataset\JPEGImages\1935.jpg</path>
	<source>
		<database>Unknown</database>
	</source>
	<size>
		<width>640</width>
		<height>480</height>
		<depth>3</depth>
	</size>
	<segmented>0</segmented>
	<object>
		<name>closed_eye</name>
		<pose>Unspecified</pose>
		<truncated>0</truncated>
		<difficult>0</difficult>
		<bndbox>
			<xmin>310</xmin>
			<ymin>229</ymin>
			<xmax>341</xmax>
			<ymax>245</ymax>
		</bndbox>
	</object>
	<object>
		<name>closed_eye</name>
		<pose>Unspecified</pose>
		<truncated>0</truncated>
		<difficult>0</difficult>
		<bndbox>
			<xmin>274</xmin>
			<ymin>246</ymin>
			<xmax>294</xmax>
			<ymax>261</ymax>
		</bndbox>
	</object>
	<object>
		<name>closed_mouth</name>
		<pose>Unspecified</pose>
		<truncated>0</truncated>
		<difficult>0</difficult>
		<bndbox>
			<xmin>304</xmin>
			<ymin>290</ymin>
			<xmax>337</xmax>
			<ymax>309</ymax>
		</bndbox>
	</object>
</annotation>
